{
    "Plot": {
        "WindowSeconds": 2.0,
        "YMin": -0.005,
        "YMax": 0.015,
        "MaxPoints": 2000,
        "RefreshIntervalMs": 250,
        "ChannelIndices": [0, 1, 4, 5],
        "ChannelLabels": {
            "0": "Uref",
            "1": "Umod",
            "2": "ch2",
            "3": "Uaux",
            "4": "Utpl",
            "5": "Uhtr"
        },
        "ChannelColors": {
            "0": "#D22525",
            "1": "#2544D2",
            "2": "#46D225",
            "3": "#9F25D2",
            "4": "#D2B325",
            "5": "#5D5D5D"
        },
        "ChannelEnabled": {
            "0": true,
            "1": true,
            "2": false,
            "3": false,
            "4": true,
            "5": true
        }
    },
    "Ring": {
        "MaxSeconds": 4.0
    },
    "Demod": {
        "WindowPeriods": 5
    },
    "DemoAO": {
        "DurationSeconds": 4.0,
        "ModulationFrequency": 37.5,
        "ModulationAmplitudeV": 2.0,
        "RampPeakV": 2.0
    },
    "Sliders": {
        "XWindowMinSeconds": 0.1,
        "XWindowMaxSeconds": 10.0,
        "XShiftMaxSeconds": 4.0,
        "YSpanMinV": 0.001,
        "YSpanMaxV": 0.1
    }
}
